aiomirai/__init__.py
aiomirai/api.py
aiomirai/api.pyi
aiomirai/event.py
aiomirai/exception.py
aiomirai/logger.py
aiomirai/message.py
aiomirai/utils.py
aiomirai/receiver/__init__.py
aiomirai/receiver/polling.py
aiomirai/receiver/report.py
aiomirai/receiver/ws.py
aiomirai-0.3.8.dist-info/LICENSE
aiomirai-0.3.8.dist-info/METADATA
aiomirai-0.3.8.dist-info/WHEEL
aiomirai-0.3.8.dist-info/top_level.txt
aiomirai-0.3.8.dist-info/RECORD
