Metadata-Version: 2.1
Name: aiomirai
Version: 0.3.8
Summary: A framework for Tencent QQ headless client 'Mirai'.
Home-page: https://github.com/AsakuraMizu/aiomirai
Author: water_lift
Author-email: 0xWATERx0@gmail.com
License: UNKNOWN
Keywords: qq mirai qqbot
Platform: UNKNOWN
Classifier: Development Status :: 3 - Alpha
Classifier: License :: OSI Approved :: GNU Affero General Public License v3
Classifier: Operating System :: OS Independent
Classifier: Intended Audience :: Developers
Classifier: Framework :: AsyncIO
Classifier: Framework :: Robot Framework
Classifier: Framework :: Robot Framework :: Library
Classifier: Topic :: Communications :: Chat
Classifier: Topic :: Internet
Classifier: Programming Language :: Python :: 3
Classifier: Programming Language :: Python :: 3.7
Classifier: Programming Language :: Python :: 3.8
Classifier: Programming Language :: Python :: 3 :: Only
Requires-Python: >=3.7
Requires-Dist: httpx (==0.13.*)
Provides-Extra: all
Requires-Dist: quart (==0.12.*) ; extra == 'all'
Requires-Dist: websockets (==8.*) ; extra == 'all'
Provides-Extra: report
Requires-Dist: quart (==0.12.*) ; extra == 'report'
Provides-Extra: ws
Requires-Dist: websockets (==8.*) ; extra == 'ws'
